world_price/__init__.py
world_price/__version__.py
world_price/adapter.py
world_price/base.py
world_price/http_utils.py
world_price/interface.py
world_price/utils.py
world_price/source/__init__.py
world_price/source/base_price_source.py
world_price/source/binance.py
world_price/source/huobi.py
world_price/source/mxc.py
world_price/source/okex.py
world_price-0.0.4.dist-info/LICENSE
world_price-0.0.4.dist-info/METADATA
world_price-0.0.4.dist-info/WHEEL
world_price-0.0.4.dist-info/top_level.txt
world_price-0.0.4.dist-info/RECORD
