Metadata-Version: 2.1
Name: world-price
Version: 0.0.4
Summary: crypto currency world price
Home-page: https://github.com/bitsoda-exchange
Author: Bitsoda Exchange
Author-email: boyang.wang@bitsoda.com
License: GPL-3.0
Project-URL: Documentation, https://github.com/bitsoda-exchange/world_price/wiki
Project-URL: Source, https://github.com/bitsoda-exchange/world_price
Platform: UNKNOWN
Classifier: Development Status :: 5 - Production/Stable
Classifier: Intended Audience :: Developers
Classifier: Natural Language :: English
Classifier: Programming Language :: Python
Classifier: Programming Language :: Python :: 3
Classifier: Programming Language :: Python :: 3.6
Classifier: Programming Language :: Python :: 3.7
Classifier: Programming Language :: Python :: 3.8
Classifier: Programming Language :: Python :: Implementation :: CPython
Classifier: Programming Language :: Python :: Implementation :: PyPy
Requires-Python: >=3.5.*
Requires-Dist: aiohttp
